lightdi/__init__.py
lightdi/core.py
tests/__init__.py
tests/test_core.py
light_dependency_injection-0.1.2.dist-info/LICENSE
light_dependency_injection-0.1.2.dist-info/METADATA
light_dependency_injection-0.1.2.dist-info/WHEEL
light_dependency_injection-0.1.2.dist-info/top_level.txt
light_dependency_injection-0.1.2.dist-info/RECORD
